{
  "title": "پلتفرم برگزاری مسابقات آنلاین بازی‌های ویدیویی",
  "actors": [
    {
      "fa": "مدیر کل",
      "en": "Main Admin",
      "kind": "primary",
      "desc": "مسئول مدیریت کلی سیستم: مدیریت ادمین‌ها، تنظیم سطوح دسترسی، مدیریت بازی‌ها و تنظیمات کلی پلتفرم."
    },
    {
      "fa": "ادمین بازی",
      "en": "Game Admin",
      "kind": "primary",
      "desc": "مسئول مدیریت مسابقات یک بازی خاص: ایجاد/ویرایش مسابقه، ثبت نتایج، مدیریت جوایز و تعامل با کاربران."
    },
    {
      "fa": "کاربر",
      "en": "User",
      "kind": "primary",
      "desc": "شرکت‌کننده در مسابقات یا بازدیدکننده پلتفرم که ثبت‌نام می‌کند، نتایج را پیگیری و جایزه دریافت می‌کند."
    },
    {
      "fa": "داور/ناظر",
      "en": "Referee",
      "kind": "primary",
      "desc": "اکتور انسانی که نتیجه‌ی بازی را تأیید می‌کند و به اعتراض‌ها و اختلاف‌های نتیجه رسیدگی می‌کند."
    },
    {
      "fa": "پشتیبانی",
      "en": "Support",
      "kind": "primary",
      "desc": "اکتور انسانی که به درخواست‌های کاربران از طریق کانال ارتباطی پاسخ می‌دهد و مسائل را پیگیری می‌کند."
    },
    {
      "fa": "درگاه پرداخت",
      "en": "PaymentGateway",
      "kind": "secondary",
      "desc": "سرویس بیرونی (زرین‌پال/Stripe) برای دریافت هزینه‌ی ثبت‌نام و واریز جایزه از کیف پول."
    },
    {
      "fa": "سرویس زمان‌بند",
      "en": "Scheduler",
      "kind": "secondary",
      "desc": "اکتور ثانویه که رفتارهای زمان‌محور را راه‌اندازی می‌کند: شروع/پایان خودکار مسابقه و ارسال اطلاع‌رسانی زمان‌بندی‌شده."
    },
    {
      "fa": "ارائه‌دهنده‌ی احراز هویت (OAuth)",
      "en": "OAuthProvider",
      "kind": "secondary",
      "desc": "سرویس بیرونی هویت (Google/Discord/Steam) برای ورود و ثبت‌نام از طریق شبکه‌های اجتماعی."
    }
  ],
  "useCases": [
    {
      "id": "UC01",
      "fa": "ورود و ثبت‌نام در پلتفرم",
      "actors": [
        "User",
        "Main Admin",
        "Game Admin",
        "Referee",
        "Support"
      ],
      "desc": "ایجاد حساب کاربری یا ورود به سیستم از طریق ایمیل، شماره تلفن یا شبکه‌های اجتماعی."
    },
    {
      "id": "UC02",
      "fa": "ورود از طریق OAuth",
      "actors": [
        "User",
        "OAuthProvider"
      ],
      "desc": "احراز هویت ورود/ثبت‌نام با حساب Google/Discord/Steam از طریق ارائه‌دهنده‌ی بیرونی."
    },
    {
      "id": "UC03",
      "fa": "انجام احراز هویت دو مرحله‌ای",
      "actors": [
        "User"
      ],
      "desc": "تأیید هویت با کد یک‌بارمصرف ایمیل یا اپلیکیشن Authenticator هنگام ورود."
    },
    {
      "id": "UC04",
      "fa": "مدیریت ادمین‌ها",
      "actors": [
        "Main Admin"
      ],
      "desc": "افزودن، ویرایش یا حذف ادمین‌های بازی توسط مدیر کل."
    },
    {
      "id": "UC05",
      "fa": "تنظیم سطوح دسترسی",
      "actors": [
        "Main Admin"
      ],
      "desc": "تخصیص دسترسی‌های خاص به ادمین‌ها (مثلاً فقط ایجاد مسابقه یا مدیریت جوایز)."
    },
    {
      "id": "UC06",
      "fa": "مدیریت بازی‌ها",
      "actors": [
        "Main Admin"
      ],
      "desc": "افزودن یا حذف بازی‌های جدید (FIFA، Warzone و غیره) از پنل مدیریت."
    },
    {
      "id": "UC07",
      "fa": "تنظیم پیکربندی سیستم",
      "actors": [
        "Main Admin"
      ],
      "desc": "تغییر تنظیمات کلی سیستم مانند درگاه پرداخت، قالب‌های پیش‌فرض و ماژول‌ها."
    },
    {
      "id": "UC08",
      "fa": "ایجاد مسابقه",
      "actors": [
        "Game Admin"
      ],
      "desc": "تعریف مسابقه‌ی جدید با عنوان، بازی، قوانین، زمان‌بندی، نوع و جوایز."
    },
    {
      "id": "UC09",
      "fa": "ویرایش یا حذف مسابقه",
      "actors": [
        "Game Admin"
      ],
      "desc": "تغییر جزئیات یا لغو مسابقات موجود."
    },
    {
      "id": "UC10",
      "fa": "ثبت و تأیید نتایج",
      "actors": [
        "Game Admin",
        "Referee"
      ],
      "desc": "وارد کردن نتایج بازی‌ها توسط ادمین و تأیید نهایی توسط داور/ناظر."
    },
    {
      "id": "UC11",
      "fa": "تأیید نتیجه‌ی بازی",
      "actors": [
        "Referee"
      ],
      "desc": "بررسی و تأیید درستی نتیجه‌ی ثبت‌شده‌ی یک بازی پیش از نهایی شدن."
    },
    {
      "id": "UC12",
      "fa": "به‌روزرسانی رده‌بندی",
      "actors": [
        "Game Admin"
      ],
      "desc": "محاسبه‌ی مجدد و به‌روزرسانی جدول رده‌بندی بر اساس نتایج تأییدشده."
    },
    {
      "id": "UC13",
      "fa": "مدیریت جوایز",
      "actors": [
        "Game Admin"
      ],
      "desc": "تعریف، تخصیص و توزیع جوایز نقدی، دیجیتال یا فیزیکی بر اساس رتبه."
    },
    {
      "id": "UC14",
      "fa": "مدیریت ماژول مسابقه",
      "actors": [
        "Game Admin"
      ],
      "desc": "تعریف قالب‌ها و قوانین اختصاصی هر مسابقه (امتیازدهی، شرایط برد/باخت، تعداد راند)."
    },
    {
      "id": "UC15",
      "fa": "ارسال اطلاع‌رسانی",
      "actors": [
        "Scheduler"
      ],
      "desc": "ارسال نوتیفیکیشن از طریق ایمیل، پیامک یا اعلان داخل اپلیکیشن، شامل اعلان‌های زمان‌بندی‌شده."
    },
    {
      "id": "UC16",
      "fa": "اجرای استریم زنده",
      "actors": [
        "Game Admin"
      ],
      "desc": "پخش زنده‌ی مسابقه از طریق پلتفرم داخلی یا اتصال به Twitch/YouTube."
    },
    {
      "id": "UC17",
      "fa": "مدیریت چت مسابقه",
      "actors": [
        "Game Admin",
        "User"
      ],
      "desc": "گفت‌وگوی زنده بین بازیکنان و ادمین‌ها در طول مسابقه."
    },
    {
      "id": "UC18",
      "fa": "بررسی گزارش تخلف",
      "actors": [
        "Game Admin",
        "Referee"
      ],
      "desc": "رسیدگی به گزارش‌های رفتار غیرمجاز ثبت‌شده توسط کاربران."
    },
    {
      "id": "UC19",
      "fa": "مشاهده مسابقات",
      "actors": [
        "User"
      ],
      "desc": "مرور مسابقات فعال، آینده و گذشته در پلتفرم."
    },
    {
      "id": "UC20",
      "fa": "ثبت‌نام در مسابقه",
      "actors": [
        "User"
      ],
      "desc": "شرکت در مسابقه پس از پرداخت هزینه‌ی ثبت‌نام در صورت نیاز."
    },
    {
      "id": "UC21",
      "fa": "پرداخت هزینه‌ی ثبت‌نام",
      "actors": [
        "User",
        "PaymentGateway"
      ],
      "desc": "پرداخت مبلغ ثبت‌نام مسابقه از طریق درگاه پرداخت."
    },
    {
      "id": "UC22",
      "fa": "پیگیری نتایج",
      "actors": [
        "User"
      ],
      "desc": "مشاهده‌ی جدول رده‌بندی و نتایج مسابقات."
    },
    {
      "id": "UC23",
      "fa": "ثبت اعتراض به نتیجه",
      "actors": [
        "User",
        "Referee"
      ],
      "desc": "ثبت اعتراض کاربر به نتیجه که توسط داور/ناظر رسیدگی می‌شود."
    },
    {
      "id": "UC24",
      "fa": "حل اختلاف نتیجه",
      "actors": [
        "Referee"
      ],
      "desc": "بررسی اعتراض‌ها و صدور رأی نهایی برای اختلاف‌های نتیجه."
    },
    {
      "id": "UC25",
      "fa": "امتیازدهی به مسابقه",
      "actors": [
        "User"
      ],
      "desc": "ارائه‌ی بازخورد و امتیاز به مسابقه توسط شرکت‌کننده."
    },
    {
      "id": "UC26",
      "fa": "ارتباط با پشتیبانی",
      "actors": [
        "User",
        "Support"
      ],
      "desc": "ارسال درخواست یا پرسش به تیم پشتیبانی از طریق کانال ارتباطی."
    },
    {
      "id": "UC27",
      "fa": "گزارش تخلف",
      "actors": [
        "User"
      ],
      "desc": "گزارش رفتار غیرمجاز یک کاربر یا مسابقه به ادمین/داور."
    },
    {
      "id": "UC28",
      "fa": "مدیریت کیف پول",
      "actors": [
        "User"
      ],
      "desc": "مشاهده‌ی موجودی، تاریخچه‌ی تراکنش و مدیریت کیف پول داخلی کاربر."
    },
    {
      "id": "UC29",
      "fa": "برداشت جایزه",
      "actors": [
        "User",
        "PaymentGateway"
      ],
      "desc": "درخواست برداشت جایزه از کیف پول به حساب بانکی کاربر."
    },
    {
      "id": "UC30",
      "fa": "انجام احراز هویت KYC",
      "actors": [
        "User"
      ],
      "desc": "احراز هویت کاربر (KYC) برای فعال‌سازی برداشت جایزه."
    },
    {
      "id": "UC31",
      "fa": "نظارت بر گزارش‌ها",
      "actors": [
        "Main Admin"
      ],
      "desc": "بررسی گزارش‌های تحلیلی پلتفرم و عملکرد بازی‌ها و مسابقات."
    }
  ],
  "relationships": [
    {
      "type": "include",
      "from": "UC20",
      "to": "UC21",
      "note": "ثبت‌نام در مسابقه همواره پرداخت هزینه‌ی ثبت‌نام را در بر می‌گیرد (پایه --> واردشده)."
    },
    {
      "type": "include",
      "from": "UC10",
      "to": "UC11",
      "note": "ثبت و تأیید نتایج شامل تأیید نتیجه‌ی بازی توسط داور است."
    },
    {
      "type": "include",
      "from": "UC10",
      "to": "UC12",
      "note": "ثبت و تأیید نتایج شامل به‌روزرسانی رده‌بندی است."
    },
    {
      "type": "include",
      "from": "UC29",
      "to": "UC30",
      "note": "برداشت جایزه شامل انجام احراز هویت KYC است (پیش‌نیاز اجباری)."
    },
    {
      "type": "include",
      "from": "UC02",
      "to": "UC01",
      "note": "ورود از طریق OAuth بخشی از فرایند ورود و ثبت‌نام را در بر می‌گیرد."
    },
    {
      "type": "include",
      "from": "UC24",
      "to": "UC11",
      "note": "حل اختلاف نتیجه شامل بازبینی و تأیید مجدد نتیجه‌ی بازی است."
    },
    {
      "type": "extend",
      "from": "UC03",
      "to": "UC01",
      "note": "احراز هویت دو مرحله‌ای به‌صورت اختیاری ورود و ثبت‌نام را گسترش می‌دهد (گسترش‌دهنده ..> پایه)."
    },
    {
      "type": "extend",
      "from": "UC27",
      "to": "UC19",
      "note": "گزارش تخلف به‌صورت اختیاری مشاهده مسابقات را گسترش می‌دهد."
    },
    {
      "type": "extend",
      "from": "UC23",
      "to": "UC22",
      "note": "ثبت اعتراض به نتیجه به‌صورت اختیاری پیگیری نتایج را گسترش می‌دهد."
    },
    {
      "type": "extend",
      "from": "UC16",
      "to": "UC08",
      "note": "اجرای استریم زنده به‌صورت اختیاری ایجاد مسابقه را گسترش می‌دهد (در صورت فعال بودن استریم)."
    },
    {
      "type": "extend",
      "from": "UC27",
      "to": "UC26",
      "note": "گزارش تخلف می‌تواند به‌صورت اختیاری ارتباط با پشتیبانی را گسترش دهد."
    }
  ],
  "decisions": [
    "تعداد و نوع نقش‌ها: اکتور غیرمجاز «سیستم خودکار (Automated System)» به‌عنوان actor primary حذف شد. به‌جای آن رفتارهای خودکار/زمان‌محور یا با include از یوزکیس انسانی مدل شدند (مثلاً ثبت و تأیید نتایج --> به‌روزرسانی رده‌بندی) یا به اکتور secondary «سرویس زمان‌بند (Scheduler)» سپرده شدند (ارسال اطلاع‌رسانی زمان‌بندی‌شده). همچنین رفتار تخصیص منابع/مقیاس‌بندی سرور چون نیازمندی غیروظیفه‌مندی زیرساختی است و هدف کاربری ندارد، از فهرست یوزکیس‌ها حذف شد.",
    "نقش‌های جاافتاده اضافه شد: «داور/ناظر (Referee)» برای تأیید نتیجه و حل اختلاف، و «پشتیبانی (Support)» برای پاسخ به درخواست‌های کاربران. هر دو به‌عنوان اکتور انسانی primary مدل شدند.",
    "اکتورهای ثانویه‌ی بیرونی اضافه شد: «درگاه پرداخت (PaymentGateway)» برای پرداخت هزینه و برداشت جایزه، «سرویس زمان‌بند (Scheduler)» برای رفتار زمان‌محور، و «ارائه‌دهنده‌ی احراز هویت OAuth (OAuthProvider)» برای ورود با شبکه‌های اجتماعی که در متن PDF (Google/Discord/Steam) آمده بود.",
    "یوزکیس ساختگی «پیش‌بینی هوش مصنوعی» حذف شد چون هدف کاربری روشن و پشتوانه‌ای در متن PDF نداشت. در نتیجه سه رابطه‌ی extend اشتباهِ متصل به آن (از مدیریت جوایز، چت و پرداخت) نیز حذف شدند.",
    "صفت‌های تزئینی «پویا/داینامیک/هوشمند/خودکار» از تمام نام یوزکیس‌ها پاک شد و همه با الگوی فعل+مفعول بازنویسی شدند (مثلاً «ثبت‌نام هوشمند» به «ثبت‌نام در مسابقه»، «پرداخت هوشمند (تأیید خودکار)» به «پرداخت هزینه‌ی ثبت‌نام»، «ثبت و اتوماسیون نتایج» به «ثبت و تأیید نتایج»).",
    "یوزکیس‌های جاافتاده‌ی متن PDF بازگردانده شد: ورود/ثبت‌نام در پلتفرم، احراز هویت دو مرحله‌ای، تنظیم سطوح دسترسی، ویرایش/حذف مسابقه، بررسی گزارش تخلف، استریم زنده، امتیازدهی به مسابقه و ارتباط با ادمین (که به «ارتباط با پشتیبانی» تصحیح شد).",
    "یوزکیس‌های کشف‌شده در بازبینی اضافه شد: تأیید نتیجه‌ی بازی، حل اختلاف/اعتراض به نتیجه (ثبت اعتراض + حل اختلاف)، احراز هویت KYC، مدیریت کیف پول و برداشت جایزه.",
    "جهت روابط طبق قرارداد اصلاح شد. include با from=پایه و to=واردشده: «ثبت‌نام در مسابقه» --> «پرداخت هزینه‌ی ثبت‌نام»، «ثبت و تأیید نتایج» --> «به‌روزرسانی رده‌بندی»، «برداشت جایزه» --> «احراز هویت KYC». extend با from=گسترش‌دهنده‌ی اختیاری و to=پایه: «گزارش تخلف» ..> «مشاهده مسابقات»، «ثبت اعتراض به نتیجه» ..> «پیگیری نتایج»، «احراز هویت دو مرحله‌ای» ..> «ورود و ثبت‌نام».",
    "رابطه‌ی اشتباه متن PDF که «ارتباط با ادمین» را شامل «گزارش تخلف» با برچسب extend می‌دانست، تصحیح شد: گزارش تخلف به‌عنوان گسترش‌دهنده‌ی اختیاری مدل شد (extend از گزارش تخلف به ارتباط با پشتیبانی و به مشاهده مسابقات)، نه برعکس.",
    "مرز سیستم یکپارچه شد: عنوان رسمی واحد «پلتفرم برگزاری مسابقات آنلاین بازی‌های ویدیویی» انتخاب شد و قید غیررسمی «(سیستم داینامیک)» از مرز سیستم حذف شد تا در نمودار و پروپوزال یکسان باشد.",
    "برچسب‌های غیرمتعارف روی خطوط ارتباط اکتور-یوزکیس (نظارت/بازخورد/هماهنگی/گزارش) که در نمودار قبلی بودند حذف شدند، چون در UML خط ارتباط اکتور با یوزکیس برچسب نمی‌گیرد."
  ]
}